{
  "$schema": "https://developer.microsoft.com/json-schemas/fabric/item/report/definition/visualContainer/2.5.0/schema.json",
  "name": "cc4e1f1914337a089c18",
  "position": {
    "x": 287.14285714285717,
    "y": 154.28571428571431,
    "z": 6000,
    "height": 465.71428571428572,
    "width": 475.71428571428572,
    "tabOrder": 6000
  },
  "visual": {
    "visualType": "clusteredBarChart",
    "query": {
      "queryState": {
        "Category": {
          "projections": [
            {
              "field": {
                "Column": {
                  "Expression": {
                    "SourceRef": {
                      "Entity": "Dim_Region"
                    }
                  },
                  "Property": "Region"
                }
              },
              "queryRef": "Dim_Region.region",
              "nativeQueryRef": "region",
              "active": true
            }
          ]
        },
        "Tooltips": {
          "projections": [
            {
              "field": {
                "Measure": {
                  "Expression": {
                    "SourceRef": {
                      "Entity": "Metric Selection"
                    }
                  },
                  "Property": "Bar Chart Sort Order"
                }
              },
              "queryRef": "Metric Selection.Bar Chart Sort Order",
              "nativeQueryRef": "Bar Chart Sort Order"
            }
          ]
        },
        "Y": {
          "projections": [
            {
              "field": {
                "Measure": {
                  "Expression": {
                    "SourceRef": {
                      "Entity": "Metric Selection"
                    }
                  },
                  "Property": "Dynamic Gap %"
                }
              },
              "queryRef": "Metric Selection.Dynamic Gap %",
              "nativeQueryRef": "Dynamic Gap %"
            }
          ]
        }
      },
      "sortDefinition": {
        "sort": [
          {
            "field": {
              "Measure": {
                "Expression": {
                  "SourceRef": {
                    "Entity": "Metric Selection"
                  }
                },
                "Property": "Bar Chart Sort Order"
              }
            },
            "direction": "Descending"
          }
        ]
      }
    },
    "objects": {
      "dataPoint": [
        {
          "properties": {
            "fill": {
              "solid": {
                "color": {
                  "expr": {
                    "FillRule": {
                      "Input": {
                        "Measure": {
                          "Expression": {
                            "SourceRef": {
                              "Entity": "Metric Selection"
                            }
                          },
                          "Property": "Dynamic Performance Score"
                        }
                      },
                      "FillRule": {
                        "linearGradient3": {
                          "min": {
                            "color": {
                              "Literal": {
                                "Value": "'#FB923C'"
                              }
                            }
                          },
                          "mid": {
                            "color": {
                              "Literal": {
                                "Value": "'#F1F5F9'"
                              }
                            }
                          },
                          "max": {
                            "color": {
                              "Literal": {
                                "Value": "'#00A396'"
                              }
                            }
                          },
                          "nullColoringStrategy": {
                            "strategy": {
                              "Literal": {
                                "Value": "'asZero'"
                              }
                            }
                          }
                        }
                      }
                    }
                  }
                }
              }
            }
          },
          "selector": {
            "data": [
              {
                "dataViewWildcard": {
                  "matchingOption": 1
                }
              }
            ]
          }
        }
      ],
      "valueAxis": [
        {
          "properties": {
            "gridlineShow": {
              "expr": {
                "Literal": {
                  "Value": "false"
                }
              }
            },
            "show": {
              "expr": {
                "Literal": {
                  "Value": "false"
                }
              }
            },
            "showAxisTitle": {
              "expr": {
                "Literal": {
                  "Value": "false"
                }
              }
            }
          }
        }
      ],
      "labels": [
        {
          "properties": {
            "show": {
              "expr": {
                "Literal": {
                  "Value": "true"
                }
              }
            },
            "bold": {
              "expr": {
                "Literal": {
                  "Value": "true"
                }
              }
            },
            "fontFamily": {
              "expr": {
                "Literal": {
                  "Value": "'''Segoe UI Semibold'', wf_segoe-ui_semibold, helvetica, arial, sans-serif'"
                }
              }
            }
          }
        }
      ],
      "categoryAxis": [
        {
          "properties": {
            "show": {
              "expr": {
                "Literal": {
                  "Value": "true"
                }
              }
            },
            "fontSize": {
              "expr": {
                "Literal": {
                  "Value": "8D"
                }
              }
            },
            "bold": {
              "expr": {
                "Literal": {
                  "Value": "true"
                }
              }
            },
            "preferredCategoryWidth": {
              "expr": {
                "Literal": {
                  "Value": "20D"
                }
              }
            },
            "showAxisTitle": {
              "expr": {
                "Literal": {
                  "Value": "false"
                }
              }
            },
            "maxMarginFactor": {
              "expr": {
                "Literal": {
                  "Value": "30L"
                }
              }
            },
            "concatenateLabels": {
              "expr": {
                "Literal": {
                  "Value": "false"
                }
              }
            }
          }
        }
      ],
      "legend": [
        {
          "properties": {
            "showGradientLegend": {
              "expr": {
                "Literal": {
                  "Value": "false"
                }
              }
            },
            "show": {
              "expr": {
                "Literal": {
                  "Value": "false"
                }
              }
            }
          }
        }
      ]
    },
    "visualContainerObjects": {
      "background": [
        {
          "properties": {
            "show": {
              "expr": {
                "Literal": {
                  "Value": "false"
                }
              }
            }
          }
        }
      ],
      "dropShadow": [
        {
          "properties": {
            "show": {
              "expr": {
                "Literal": {
                  "Value": "true"
                }
              }
            }
          }
        }
      ],
      "title": [
        {
          "properties": {
            "show": {
              "expr": {
                "Literal": {
                  "Value": "true"
                }
              }
            },
            "text": {
              "expr": {
                "Measure": {
                  "Expression": {
                    "SourceRef": {
                      "Entity": "Metric Selection"
                    }
                  },
                  "Property": "Bar Chart Dynamic Title"
                }
              }
            },
            "fontColor": {
              "solid": {
                "color": {
                  "expr": {
                    "Literal": {
                      "Value": "'#312E81'"
                    }
                  }
                }
              }
            },
            "alignment": {
              "expr": {
                "Literal": {
                  "Value": "'center'"
                }
              }
            },
            "fontFamily": {
              "expr": {
                "Literal": {
                  "Value": "'''Segoe UI Semibold'', wf_segoe-ui_semibold, helvetica, arial, sans-serif'"
                }
              }
            },
            "fontSize": {
              "expr": {
                "Literal": {
                  "Value": "13D"
                }
              }
            }
          }
        }
      ],
      "visualTooltip": [
        {
          "properties": {
            "section": {
              "expr": {
                "Literal": {
                  "Value": "'e760511c7833a1464469'"
                }
              }
            }
          }
        }
      ]
    },
    "drillFilterOtherVisuals": true
  }
}